README.rst
setup.py
cathy/__init__.py
cathy/__main__.py
cathy/std-startup.xml
cathy.egg-info/PKG-INFO
cathy.egg-info/SOURCES.txt
cathy.egg-info/dependency_links.txt
cathy.egg-info/entry_points.txt
cathy.egg-info/not-zip-safe
cathy.egg-info/requires.txt
cathy.egg-info/top_level.txt
cathy/aiml/alice/ai.aiml
cathy/aiml/alice/alice.aiml
cathy/aiml/alice/astrology.aiml
cathy/aiml/alice/atomic.aiml
cathy/aiml/alice/badanswer.aiml
cathy/aiml/alice/biography.aiml
cathy/aiml/alice/bot.aiml
cathy/aiml/alice/bot_profile.aiml
cathy/aiml/alice/client.aiml
cathy/aiml/alice/client_profile.aiml
cathy/aiml/alice/computers.aiml
cathy/aiml/alice/continuation.aiml
cathy/aiml/alice/date.aiml
cathy/aiml/alice/default.aiml
cathy/aiml/alice/drugs.aiml
cathy/aiml/alice/emotion.aiml
cathy/aiml/alice/food.aiml
cathy/aiml/alice/geography.aiml
cathy/aiml/alice/gossip.aiml
cathy/aiml/alice/history.aiml
cathy/aiml/alice/humor.aiml
cathy/aiml/alice/imponderables.aiml
cathy/aiml/alice/inquiry.aiml
cathy/aiml/alice/interjection.aiml
cathy/aiml/alice/iu.aiml
cathy/aiml/alice/knowledge.aiml
cathy/aiml/alice/literature.aiml
cathy/aiml/alice/loebner10.aiml
cathy/aiml/alice/money.aiml
cathy/aiml/alice/movies.aiml
cathy/aiml/alice/mp0.aiml
cathy/aiml/alice/mp1.aiml
cathy/aiml/alice/mp2.aiml
cathy/aiml/alice/mp3.aiml
cathy/aiml/alice/mp4.aiml
cathy/aiml/alice/mp5.aiml
cathy/aiml/alice/mp6.aiml
cathy/aiml/alice/music.aiml
cathy/aiml/alice/numbers.aiml
cathy/aiml/alice/personality.aiml
cathy/aiml/alice/phone.aiml
cathy/aiml/alice/pickup.aiml
cathy/aiml/alice/politics.aiml
cathy/aiml/alice/primeminister.aiml
cathy/aiml/alice/primitive-math.aiml
cathy/aiml/alice/psychology.aiml
cathy/aiml/alice/pyschology.aiml
cathy/aiml/alice/reduction.names.aiml
cathy/aiml/alice/reduction0.safe.aiml
cathy/aiml/alice/reduction1.safe.aiml
cathy/aiml/alice/reduction2.safe.aiml
cathy/aiml/alice/reduction3.safe.aiml
cathy/aiml/alice/reduction4.safe.aiml
cathy/aiml/alice/reductions-update.aiml
cathy/aiml/alice/religion.aiml
cathy/aiml/alice/salutations.aiml
cathy/aiml/alice/science.aiml
cathy/aiml/alice/sex.aiml
cathy/aiml/alice/sports.aiml
cathy/aiml/alice/stack.aiml
cathy/aiml/alice/stories.aiml
cathy/aiml/alice/that.aiml
