Metadata-Version: 1.2
Name: cathy
Version: 4.0.0
Summary: Discord chat bot using AIML artificial intelligence.
Home-page: https://github.com/DevDungeon/ChattyCathy
Author: DevDungeon
Author-email: nanodano@devdungeon.com
License: GPL-3.0
Platform: UNKNOWN
Requires-Python: >=3.7
